itk/FpfhPython.py
itk/_FpfhPython.pyd
itk/__init_fpfh__.py
itk/itkPointFeaturePython.py
itk/Configuration/FpfhConfig.py
itk/Configuration/Fpfh_snake_case.py
itk_fpfh.libs/.load-order-itk_fpfh-0.1.1
itk_fpfh.libs/msvcp140.dll
itk_fpfh.libs/tbb12.dll
itk_fpfh-0.1.1.dist-info/DELVEWHEEL
itk_fpfh-0.1.1.dist-info/LICENSE
itk_fpfh-0.1.1.dist-info/METADATA
itk_fpfh-0.1.1.dist-info/WHEEL
itk_fpfh-0.1.1.dist-info/top_level.txt
itk_fpfh-0.1.1.dist-info/RECORD
